memory/imem.sv
module imem(input logic [31:0]Q,
            output logic [31:0]out);
    logic [31:0] array[4];

    initial begin
        //32bitでデータを代入(32bit長のarrayに)
        array[0] = 32'b0000;
        array[1] = 32'b0001;
        array[2] = 32'b0010;
        array[3] = 32'b0011;
    end

    //assignで常に繋げる
    assign out = array[Q];
endmodule

core/counter/counter.sv
module counter (input logic Clk,
                input logic reset,
                output logic [31:0] q);

    //resetはフリップフロップ(q)の初期化信号
    //この場合resetが1の時に初期化としてqは0を吐き出す（ゴミデータ排除のため）
    //counter_testの記述によって、resetが立ち下がった時に初期化が終わり
    //フリップフロップ本来の機能（カウンタ）が始まる
    always_ff @( posedge Clk, posedge reset )
        if(reset) q <= 0;
        else      q <= q + 1;
endmodule

testbench/counter_test.sv
module counter_test();
    logic Clk,reset;
    logic [31:0] q;
    logic [31:0] Q;
    logic [31:0] out;

    counter dut1(Clk,reset,q);
    imem dut2(Q,out);

    //クロック生成
    always #5 Clk = ~Clk;


    initial begin
       reset = 1;
       Clk = 1;
       #10
       reset = 0; 
       #500;
       $finish;
    end
    
    assign Q = q;


    initial begin
       $monitor("Clk=%d, reset=%d, q=%d, Q=%d, out=%d", Clk, reset, q, Q, out);
       $dumpfile("counter.vcd");
       $dumpvars(0, counter_test);
    end
endmodule

core/counter/counter.vcd
$date
	Sun Feb 05 00:58:54 2023
$end
$version
	Icarus Verilog
$end
$timescale
	1s
$end
$scope module counter_test $end
$var wire 32 ! Q [31:0] $end
$var wire 32 " q [31:0] $end
$var wire 32 # out [31:0] $end
$var reg 1 $ Clk $end
$var reg 1 % reset $end
$scope module dut1 $end
$var wire 1 $ Clk $end
$var wire 1 % reset $end
$var reg 32 & q [31:0] $end
$upscope $end
$scope module dut2 $end
$var wire 32 ' Q [31:0] $end
$var wire 32 ( out [31:0] $end
$upscope $end
$upscope $end
$enddefinitions $end
$comment Show the parameter values. $end
$dumpall
$end
#0
$dumpvars
b0 (
b0 '
b0 &
1%
1$
b0 #
b0 "
b0 !
$end
#5
0$
#10
b1 #
b1 (
b1 !
b1 '
b1 "
b1 &
1$
0%
#15
0$
#20
b10 #
b10 (
b10 !
b10 '
b10 "
b10 &
1$
#25
0$
#30
b11 #
b11 (
b11 !
b11 '
b11 "
b11 &
1$
#35
0$
#40
bx #
bx (
b100 !
b100 '
b100 "
b100 &
1$
#45
0$
#50
b101 !
b101 '
b101 "
b101 &
1$
#55
0$
#60
b110 !
b110 '
b110 "
b110 &
1$
#65
0$
#70
b111 !
b111 '
b111 "
b111 &
1$
#75
0$
#80
b1000 !
b1000 '
b1000 "
b1000 &
1$
#85
0$
#90
b1001 !
b1001 '
b1001 "
b1001 &
1$
#95
0$
#100
b1010 !
b1010 '
b1010 "
b1010 &
1$
#105
0$
#110
b1011 !
b1011 '
b1011 "
b1011 &
1$
#115
0$
#120
b1100 !
b1100 '
b1100 "
b1100 &
1$
#125
0$
#130
b1101 !
b1101 '
b1101 "
b1101 &
1$
#135
0$
#140
b1110 !
b1110 '
b1110 "
b1110 &
1$
#145
0$
#150
b1111 !
b1111 '
b1111 "
b1111 &
1$
#155
0$
#160
b10000 !
b10000 '
b10000 "
b10000 &
1$
#165
0$
#170
b10001 !
b10001 '
b10001 "
b10001 &
1$
#175
0$
#180
b10010 !
b10010 '
b10010 "
b10010 &
1$
#185
0$
#190
b10011 !
b10011 '
b10011 "
b10011 &
1$
#195
0$
#200
b10100 !
b10100 '
b10100 "
b10100 &
1$
#205
0$
#210
b10101 !
b10101 '
b10101 "
b10101 &
1$
#215
0$
#220
b10110 !
b10110 '
b10110 "
b10110 &
1$
#225
0$
#230
b10111 !
b10111 '
b10111 "
b10111 &
1$
#235
0$
#240
b11000 !
b11000 '
b11000 "
b11000 &
1$
#245
0$
#250
b11001 !
b11001 '
b11001 "
b11001 &
1$
#255
0$
#260
b11010 !
b11010 '
b11010 "
b11010 &
1$
#265
0$
#270
b11011 !
b11011 '
b11011 "
b11011 &
1$
#275
0$
#280
b11100 !
b11100 '
b11100 "
b11100 &
1$
#285
0$
#290
b11101 !
b11101 '
b11101 "
b11101 &
1$
#295
0$
#300
b11110 !
b11110 '
b11110 "
b11110 &
1$
#305
0$
#310
b11111 !
b11111 '
b11111 "
b11111 &
1$
#315
0$
#320
b100000 !
b100000 '
b100000 "
b100000 &
1$
#325
0$
#330
b100001 !
b100001 '
b100001 "
b100001 &
1$
#335
0$
#340
b100010 !
b100010 '
b100010 "
b100010 &
1$
#345
0$
#350
b100011 !
b100011 '
b100011 "
b100011 &
1$
#355
0$
#360
b100100 !
b100100 '
b100100 "
b100100 &
1$
#365
0$
#370
b100101 !
b100101 '
b100101 "
b100101 &
1$
#375
0$
#380
b100110 !
b100110 '
b100110 "
b100110 &
1$
#385
0$
#390
b100111 !
b100111 '
b100111 "
b100111 &
1$
#395
0$
#400
b101000 !
b101000 '
b101000 "
b101000 &
1$
#405
0$
#410
b101001 !
b101001 '
b101001 "
b101001 &
1$
#415
0$
#420
b101010 !
b101010 '
b101010 "
b101010 &
1$
#425
0$
#430
b101011 !
b101011 '
b101011 "
b101011 &
1$
#435
0$
#440
b101100 !
b101100 '
b101100 "
b101100 &
1$
#445
0$
#450
b101101 !
b101101 '
b101101 "
b101101 &
1$
#455
0$
#460
b101110 !
b101110 '
b101110 "
b101110 &
1$
#465
0$
#470
b101111 !
b101111 '
b101111 "
b101111 &
1$
#475
0$
#480
b110000 !
b110000 '
b110000 "
b110000 &
1$
#485
0$
#490
b110001 !
b110001 '
b110001 "
b110001 &
1$
#495
0$
#500
b110010 !
b110010 '
b110010 "
b110010 &
1$
#505
0$
#510
b110011 !
b110011 '
b110011 "
b110011 &
1$
